sure/__init__.py
sure/cli.py
sure/compat.py
sure/core.py
sure/deprecated.py
sure/magic.py
sure/old.py
sure/registry.py
sure/stubs.py
sure/terminal.py
sure/version.py
surer-0.0.3.dist-info/COPYING
surer-0.0.3.dist-info/METADATA
surer-0.0.3.dist-info/WHEEL
surer-0.0.3.dist-info/top_level.txt
surer-0.0.3.dist-info/RECORD
