Metadata-Version: 2.1
Name: surer
Version: 0.0.3
Home-page: https://github.com/getmoto/surer
Author: Gabriel Falcao
Author-email: "gabriel@nacaolivre.org"
Maintainer: Bert Blommers
License: Apache License 2.0
Project-URL: Documentation, https://surer.readthedocs.io/en/latest/
Project-URL: Issue tracker, https://github.com/getmoto/surer/issues
Keywords: test assertions fluent
Classifier: Programming Language :: Python :: 3
Classifier: Programming Language :: Python :: 3.6
Classifier: Programming Language :: Python :: 3.7
Classifier: Programming Language :: Python :: 3.8
Classifier: Programming Language :: Python :: 3.9
Classifier: Programming Language :: Python :: 3.10
Classifier: Programming Language :: Python :: 3.11
Classifier: License :: OSI Approved :: Apache Software License
Classifier: Topic :: Software Development :: Testing
Requires-Python: >=3.6
License-File: COPYING
